eidas_node/__init__.py
eidas_node/attributes.py
eidas_node/constants.py
eidas_node/datamodels.py
eidas_node/errors.py
eidas_node/models.py
eidas_node/saml.py
eidas_node/settings.py
eidas_node/utils.py
eidas_node/xml.py
eidas_node/__pycache__/__init__.cpython-310.pyc
eidas_node/connector/__init__.py
eidas_node/connector/apps.py
eidas_node/connector/settings.py
eidas_node/connector/urls.py
eidas_node/connector/views.py
eidas_node/connector/demo/__init__.py
eidas_node/connector/demo/urls.py
eidas_node/connector/demo/views.py
eidas_node/connector/static/eidas_node/connector/formautosubmit.js
eidas_node/connector/static/eidas_node/connector/css/flags.css
eidas_node/connector/static/eidas_node/connector/css/screen.css
eidas_node/connector/static/eidas_node/connector/img/flags/LICENSE
eidas_node/connector/static/eidas_node/connector/img/flags/at.svg
eidas_node/connector/static/eidas_node/connector/img/flags/be.svg
eidas_node/connector/static/eidas_node/connector/img/flags/bg.svg
eidas_node/connector/static/eidas_node/connector/img/flags/cy.svg
eidas_node/connector/static/eidas_node/connector/img/flags/cz.svg
eidas_node/connector/static/eidas_node/connector/img/flags/de.svg
eidas_node/connector/static/eidas_node/connector/img/flags/dk.svg
eidas_node/connector/static/eidas_node/connector/img/flags/ee.svg
eidas_node/connector/static/eidas_node/connector/img/flags/es.svg
eidas_node/connector/static/eidas_node/connector/img/flags/fi.svg
eidas_node/connector/static/eidas_node/connector/img/flags/fr.svg
eidas_node/connector/static/eidas_node/connector/img/flags/gb.svg
eidas_node/connector/static/eidas_node/connector/img/flags/gr.svg
eidas_node/connector/static/eidas_node/connector/img/flags/hr.svg
eidas_node/connector/static/eidas_node/connector/img/flags/hu.svg
eidas_node/connector/static/eidas_node/connector/img/flags/ie.svg
eidas_node/connector/static/eidas_node/connector/img/flags/is.svg
eidas_node/connector/static/eidas_node/connector/img/flags/it.svg
eidas_node-0.9.0.dist-info/LICENSE
eidas_node-0.9.0.dist-info/METADATA
eidas_node-0.9.0.dist-info/WHEEL
eidas_node-0.9.0.dist-info/top_level.txt
eidas_node-0.9.0.dist-info/RECORD
