Metadata-Version: 2.1
Name: eidas-node
Version: 0.9.0
Summary: An implementation of eIDAS-Node 2.3.x Specific Connector and Proxy Service.
Home-page: https://github.com/CZ-NIC/django-eidas-specific-node
Author: Jiří Janoušek
Author-email: jiri.janousek@nic.cz
License: UNKNOWN
Platform: UNKNOWN
Classifier: License :: OSI Approved :: GNU General Public License v3 or later (GPLv3+)
Requires-Python: ~=3.5
License-File: LICENSE
Requires-Dist: django (<2.3,>=2.2)
Requires-Dist: django-app-settings (>=0.7.1)
Requires-Dist: lxml
Requires-Dist: xmlsec
Provides-Extra: ignite
Requires-Dist: pyignite ; extra == 'ignite'
Provides-Extra: quality
Requires-Dist: isort ; extra == 'quality'
Requires-Dist: flake8 ; extra == 'quality'
Requires-Dist: pydocstyle ; extra == 'quality'
Requires-Dist: mypy ; extra == 'quality'
Provides-Extra: tests
Requires-Dist: freezegun ; extra == 'tests'
